<annotation>
	<folder>Image</folder>
	<filename>1110_campegli_18_10_2020__16_04_44.png</filename>
	<path>C:\Users\Filippo\Desktop\Image\1110_campegli_18_10_2020__16_04_44.png</path>
	<source>
		<database>Unknown</database>
	</source>
	<size>
		<width>1280</width>
		<height>857</height>
		<depth>3</depth>
	</size>
	<segmented>0</segmented>
	<object>
		<name>maybe</name>
		<pose>Unspecified</pose>
		<truncated>0</truncated>
		<difficult>0</difficult>
		<bndbox>
			<xmin>968</xmin>
			<ymin>209</ymin>
			<xmax>1203</xmax>
			<ymax>365</ymax>
		</bndbox>
	</object>
	<object>
		<name>maybe</name>
		<pose>Unspecified</pose>
		<truncated>0</truncated>
		<difficult>0</difficult>
		<bndbox>
			<xmin>15</xmin>
			<ymin>422</ymin>
			<xmax>123</xmax>
			<ymax>674</ymax>
		</bndbox>
	</object>
</annotation>
