<annotation>
	<folder>data_raw</folder>
	<filename>1699_nw_veulettes2_18_10_2020__14_20_09.png</filename>
	<path>/media/sebastiano/Data/windspeed/data_raw/1699_nw_veulettes2_18_10_2020__14_20_09.png</path>
	<source>
		<database>Unknown</database>
	</source>
	<size>
		<width>1280</width>
		<height>857</height>
		<depth>3</depth>
	</size>
	<segmented>0</segmented>
	<object>
		<name>yes</name>
		<pose>Unspecified</pose>
		<truncated>0</truncated>
		<difficult>0</difficult>
		<bndbox>
			<xmin>919</xmin>
			<ymin>291</ymin>
			<xmax>1115</xmax>
			<ymax>464</ymax>
		</bndbox>
	</object>
	<object>
		<name>yes</name>
		<pose>Unspecified</pose>
		<truncated>0</truncated>
		<difficult>0</difficult>
		<bndbox>
			<xmin>1141</xmin>
			<ymin>292</ymin>
			<xmax>1279</xmax>
			<ymax>457</ymax>
		</bndbox>
	</object>
</annotation>
