<annotation>
	<folder>data_raw</folder>
	<filename>2109_nw_veulettes_17_10_2020__17_49_59.png</filename>
	<path>/media/sebastiano/Data/windspeed/data_raw/2109_nw_veulettes_17_10_2020__17_49_59.png</path>
	<source>
		<database>Unknown</database>
	</source>
	<size>
		<width>1280</width>
		<height>857</height>
		<depth>3</depth>
	</size>
	<segmented>0</segmented>
	<object>
		<name>no</name>
		<pose>Unspecified</pose>
		<truncated>0</truncated>
		<difficult>0</difficult>
		<bndbox>
			<xmin>324</xmin>
			<ymin>375</ymin>
			<xmax>360</xmax>
			<ymax>487</ymax>
		</bndbox>
	</object>
	<object>
		<name>no</name>
		<pose>Unspecified</pose>
		<truncated>0</truncated>
		<difficult>0</difficult>
		<bndbox>
			<xmin>426</xmin>
			<ymin>386</ymin>
			<xmax>454</xmax>
			<ymax>467</ymax>
		</bndbox>
	</object>
	<object>
		<name>no</name>
		<pose>Unspecified</pose>
		<truncated>0</truncated>
		<difficult>0</difficult>
		<bndbox>
			<xmin>491</xmin>
			<ymin>384</ymin>
			<xmax>518</xmax>
			<ymax>467</ymax>
		</bndbox>
	</object>
	<object>
		<name>no</name>
		<pose>Unspecified</pose>
		<truncated>0</truncated>
		<difficult>0</difficult>
		<bndbox>
			<xmin>550</xmin>
			<ymin>388</ymin>
			<xmax>571</xmax>
			<ymax>472</ymax>
		</bndbox>
	</object>
</annotation>
