<annotation>
	<folder>Flag</folder>
	<filename>images94 (4).jpg</filename>
	<path>D:\ME\gugli\Bocconi\5\1_sem\comp_vision\project\Flag\images94 (4).jpg</path>
	<source>
		<database>Unknown</database>
	</source>
	<size>
		<width>301</width>
		<height>168</height>
		<depth>3</depth>
	</size>
	<segmented>0</segmented>
	<object>
		<name>Flag</name>
		<pose>Unspecified</pose>
		<truncated>0</truncated>
		<difficult>0</difficult>
		<bndbox>
			<xmin>151</xmin>
			<ymin>25</ymin>
			<xmax>231</xmax>
			<ymax>118</ymax>
		</bndbox>
	</object>
</annotation>
