<annotation>
	<folder>Flag</folder>
	<filename>bandiera-italia.jpg</filename>
	<path>D:\ME\gugli\Bocconi\5\1_sem\comp_vision\project\Flag\bandiera-italia.jpg</path>
	<source>
		<database>Unknown</database>
	</source>
	<size>
		<width>700</width>
		<height>487</height>
		<depth>3</depth>
	</size>
	<segmented>0</segmented>
	<object>
		<name>Flag</name>
		<pose>Unspecified</pose>
		<truncated>0</truncated>
		<difficult>0</difficult>
		<bndbox>
			<xmin>50</xmin>
			<ymin>61</ymin>
			<xmax>664</xmax>
			<ymax>454</ymax>
		</bndbox>
	</object>
</annotation>
